[
    {
        "id": "00000000-0000-0000-0000-000000000000",
        "name": "South Whidbey Park",
        "description": "Something for the whole family. Only complaint I can make is I wish there was something like a giant quater pipe on the open end to connect it all together. But you can get some decent speed crusing this place. Plus there's a giant 'Castle Park' along with play fields so there is something for everyone here. A great addition to the South End.",
        "address": {
            "addressLine1": "5481 Maxwelton Rd",
            "addressLine2": "",
            "city": "Langley",
            "state": "WA",
            "zipCode": "98260",
            "googleMaps": {
                "embedMap": "\u003ciframe src=\"https://www.google.com/maps/embed?pb=!1m14!1m12!1m3!1d619.2444088055857!2d-122.40718625959809!3d48.00859390566867!2m3!1f0!2f0!3f0!3m2!1i1024!2i768!4f13.1!5e1!3m2!1sen!2sus!4v1503010089945\" frameborder=\"0\" style=\"border:0; width: 100%; height: 100%;\" allowfullscreen\u003e\u003c/iframe\u003e",
                "ShareLink": "https://www.google.com/maps/@48.0085939,-122.4071863,142m/data=!3m1!1e3"
            }
        },
        "albumId": "pj2dc",
        "album": {
            "id": "pj2dc",
            "title": "skatepark - wa - whidbey island (south)",
            "description": null,
            "images": [
                {
                    "id": "rKo9SSV",
                    "link": "https://i.imgur.com/rKo9SSV.jpg",
                    "title": null,
                    "name": null,
                    "description": "Has a nice sized mini-ramp."
                },
                {
                    "id": "duDuOzU",
                    "link": "https://i.imgur.com/duDuOzU.jpg",
                    "title": null,
                    "name": null,
                    "description": "Got a 3 ft quarter pipe enclosing the other end."
                },
                {
                    "id": "XmqRY3f",
                    "link": "https://i.imgur.com/XmqRY3f.jpg",
                    "title": null,
                    "name": null,
                    "description": "It's got nice smooth concrete."
                },
                {
                    "id": "TRbR45t",
                    "link": "https://i.imgur.com/TRbR45t.jpg",
                    "title": null,
                    "name": null,
                    "description": "Lots of ledges but most of them are kinked and down a steep bank."
                },
                {
                    "id": "6p8OAKq",
                    "link": "https://i.imgur.com/6p8OAKq.jpg",
                    "title": null,
                    "name": null,
                    "description": "Roll down a bank into the quarter pipe."
                },
                {
                    "id": "W2xEREG",
                    "link": "https://i.imgur.com/W2xEREG.jpg",
                    "title": null,
                    "name": null,
                    "description": "'Table top' with ledges."
                },
                {
                    "id": "hfsli4S",
                    "link": "https://i.imgur.com/hfsli4S.jpg",
                    "title": null,
                    "name": null,
                    "description": "Wish they had a giant quarter pipe enclosing the entire park in the distance."
                },
                {
                    "id": "zVnXCYj",
                    "link": "https://i.imgur.com/zVnXCYj.jpg",
                    "title": null,
                    "name": null,
                    "description": "Extension on the mini-ramp."
                },
                {
                    "id": "jHRFjdj",
                    "link": "https://i.imgur.com/jHRFjdj.jpg",
                    "title": null,
                    "name": null,
                    "description": "Over the table top and into the mini-ramp."
                },
                {
                    "id": "22RaqIa",
                    "link": "https://i.imgur.com/22RaqIa.jpg",
                    "title": null,
                    "name": null,
                    "description": "Quarter pipe has a roll in section."
                },
                {
                    "id": "wqYEkDL",
                    "link": "https://i.imgur.com/wqYEkDL.jpg",
                    "title": null,
                    "name": null,
                    "description": "A stair set but I'm not sure you can even ollie this thing as it's got a short runway."
                },
                {
                    "id": "41TDlll",
                    "link": "https://i.imgur.com/41TDlll.jpg",
                    "title": null,
                    "name": null,
                    "description": "Flat bar."
                },
                {
                    "id": "7oOsf7t",
                    "link": "https://i.imgur.com/7oOsf7t.jpg",
                    "title": null,
                    "name": null,
                    "description": "On the top deck."
                },
                {
                    "id": "hnOs1gX",
                    "link": "https://i.imgur.com/hnOs1gX.jpg",
                    "title": null,
                    "name": null,
                    "description": "Look at all those ledges."
                },
                {
                    "id": "HOn6nnb",
                    "link": "https://i.imgur.com/HOn6nnb.jpg",
                    "title": null,
                    "name": null,
                    "description": "Always enjoi."
                },
                {
                    "id": "i4uCMoq",
                    "link": "https://i.imgur.com/i4uCMoq.jpg",
                    "title": null,
                    "name": null,
                    "description": "This park has a good flow, it's just not the lines you would first expect."
                },
                {
                    "id": "R6LiYzz",
                    "link": "https://i.imgur.com/R6LiYzz.jpg",
                    "title": null,
                    "name": null,
                    "description": "Mini-ramp."
                },
                {
                    "id": "rjV1OSo",
                    "link": "https://i.imgur.com/rjV1OSo.jpg",
                    "title": null,
                    "name": null,
                    "description": "Mini-ramp with hip with 1 ft extension and optional roll in."
                },
                {
                    "id": "0fPbh1C",
                    "link": "https://i.imgur.com/0fPbh1C.jpg",
                    "title": null,
                    "name": null,
                    "description": "Panorama. Has a nice large park around the skatepark for all to enjoy."
                },
                {
                    "id": "oWM14br",
                    "link": "https://i.imgur.com/oWM14br.jpg",
                    "title": null,
                    "name": null,
                    "description": "The park donors."
                }
            ]
        }
    }
]